fundamentals_of_data_science/__init__.py
fundamentals_of_data_science/eda.py
fundamentals_of_data_science/fundamentals_of_data_science.py
fundamentals_of_data_science/models.py
fundamentals_of_data_science/datasets/__init__.py
fundamentals_of_data_science/datasets/arsenic.wells.tsv
fundamentals_of_data_science/datasets/child_iq.tsv
fundamentals_of_data_science/datasets/imports-85.data.csv
fundamentals_of_data_science/datasets/kc_house_data.csv
fundamentals_of_data_science/datasets/mesquite.tsv
fundamentals_of_data_science-0.2.0.dist-info/AUTHORS.rst
fundamentals_of_data_science-0.2.0.dist-info/LICENSE
fundamentals_of_data_science-0.2.0.dist-info/METADATA
fundamentals_of_data_science-0.2.0.dist-info/WHEEL
fundamentals_of_data_science-0.2.0.dist-info/top_level.txt
fundamentals_of_data_science-0.2.0.dist-info/RECORD
