Metadata-Version: 2.1
Name: fundamentals-of-data-science
Version: 0.2.0
Summary: Companion Python package for Fundamentals of Data Science.
Home-page: https://github.com/fundamentals-of-data-science/ds-fundamentals-python
Author: Andrew Stewart
Author-email: andrew.c.stewart@gmail.com
License: MIT license
Keywords: fundamentals_of_data_science
Platform: UNKNOWN
Classifier: Development Status :: 2 - Pre-Alpha
Classifier: Intended Audience :: Developers
Classifier: License :: OSI Approved :: MIT License
Classifier: Natural Language :: English
Classifier: Programming Language :: Python :: 2
Classifier: Programming Language :: Python :: 2.7
Classifier: Programming Language :: Python :: 3
Classifier: Programming Language :: Python :: 3.4
Classifier: Programming Language :: Python :: 3.5
Classifier: Programming Language :: Python :: 3.6
Classifier: Programming Language :: Python :: 3.7
Requires-Dist: numpy
Requires-Dist: scipy
Requires-Dist: pandas
Requires-Dist: matplotlib
Requires-Dist: seaborn
Requires-Dist: statsmodels
Requires-Dist: sklearn
Requires-Dist: patsy
